{
  "rings": [
    {
      "id": "adopt",
      "name": "ADOPT",
      "color": "#93c47d"
    },
    {
      "id": "trial",
      "name": "TRIAL",
      "color": "#93d2c2"
    },
    {
      "id": "assess",
      "name": "ASSESS",
      "color": "#fbdb84"
    },
    {
      "id": "hold",
      "name": "HOLD",
      "color": "#efafa9"
    }
  ],
  "quadrants": [
    {
      "id": "infrastructure",
      "name": "Infrastructure"
    },
    {
      "id": "tools",
      "name": "Tools"
    },
    {
      "id": "languages",
      "name": "Languages"
    },
    {
      "id": "techniques",
      "name": "Techniques"
    }
  ],
  "entries": [
    {
      "timeline": [
        {
          "moved": 0,
          "ringId": "adopt",
          "date": "2020-08-06T00:00:00.000Z",
          "license": "Apache License 2.0",
          "description": "Open source system for managing containerized applications across multiple hosts. It provides basic mechanisms for deployment, maintenance, and scaling of applications."
        }
      ],
      "url": "#",
      "key": "kubernetes",
      "id": "kubernetes",
      "title": "Kubernetes",
      "quadrant": "infrastructure"
    },
    {
      "timeline": [
        {
          "moved": 0,
          "ringId": "adopt",
          "date": "2020-08-06T00:00:00.000Z",
          "license": "MIT License",
          "description": "GitLab is an open source end-to-end software development platform with built-in version control, issue tracking, code review, CI/CD, and more. Self-host GitLab on your own servers, in a container, or on a cloud provider."
        }
      ],
      "url": "#",
      "key": "gitlab",
      "id": "gitlab",
      "title": "GitLab",
      "quadrant": "infrastructure"
    },
    {
      "timeline": [
        {
          "moved": 0,
          "ringId": "adopt",
          "date": "2020-08-06T00:00:00.000Z",
          "license": "Apache License 2.0",
          "description": "ArgoCD is a declarative GitOps tool built to deploy applications to Kubernetes."
        }
      ],
      "url": "#",
      "key": "argocd",
      "id": "argocd",
      "title": "ArgoCD",
      "quadrant": "infrastructure"
    },
    {
      "timeline": [
        {
          "moved": 0,
          "ringId": "adopt",
          "date": "2020-08-06T00:00:00.000Z",
          "license": "Mozilla Public License 2.0",
          "description": "Vault is a tool for securely accessing secrets. A secret is anything that you want to tightly control access to, such as API keys, passwords, certificates, and more. Vault provides a unified interface to any secret, while providing tight access control and recording a detailed audit log."
        }
      ],
      "url": "#",
      "key": "vault",
      "id": "vault",
      "title": "HashiCorp Vault",
      "quadrant": "infrastructure"
    },
    {
      "timeline": [
        {
          "moved": 0,
          "ringId": "adopt",
          "date": "2020-08-06T00:00:00.000Z",
          "license": "GNU Lesser General Public License v3.0",
          "description": "Open-source platform developed by SonarSource for continuous inspection of code quality to perform automatic reviews with static analysis of code to detect bugs, code smells on 17 programming languages."
        }
      ],
      "url": "#",
      "key": "sonarqube",
      "id": "sonarqube",
      "title": "SonarQube",
      "quadrant": "infrastructure"
    },
    {
      "timeline": [
        {
          "moved": 0,
          "ringId": "adopt",
          "date": "2020-08-06T00:00:00.000Z",
          "license": "Eclipse Public License 1.0",
          "description": "Binary repository management."
        }
      ],
      "url": "#",
      "key": "nexus",
      "id": "nexus",
      "title": "Nexus",
      "quadrant": "infrastructure"
    },
    {
      "timeline": [
        {
          "moved": 0,
          "ringId": "adopt",
          "date": "2020-08-06T00:00:00.000Z",
          "license": "GNU Affero General Public License v3.0",
          "description": "The open-source platform for monitoring and observability. Grafana allows you to query, visualize, alert on and understand your metrics no matter where they are stored. Create, explore, and share dashboards with your team and foster a data-driven culture."
        }
      ],
      "url": "#",
      "key": "grafana",
      "id": "grafana",
      "title": "Grafana",
      "quadrant": "infrastructure"
    },
    {
      "timeline": [
        {
          "moved": 0,
          "ringId": "adopt",
          "date": "2020-08-06T00:00:00.000Z",
          "license": "Apache License 2.0",
          "description": "Prometheus, a Cloud Native Computing Foundation project, is a systems and service monitoring system. It collects metrics from configured targets at given intervals, evaluates rule expressions, displays the results, and can trigger alerts when specified conditions are observed."
        }
      ],
      "url": "#",
      "key": "prometheus",
      "id": "prometheus",
      "title": "Prometheus",
      "quadrant": "infrastructure"
    },
    {
      "timeline": [
        {
          "moved": 0,
          "ringId": "adopt",
          "date": "2020-08-06T00:00:00.000Z",
          "license": "Apache License 2.0",
          "description": "OpenSearch is a community-driven, open source fork of Elasticsearch and Kibana following the licence change in early 2021."
        }
      ],
      "url": "#",
      "key": "opensearch",
      "id": "opensearch",
      "title": "OpenSearch",
      "quadrant": "infrastructure"
    },
    {
      "timeline": [
        {
          "moved": 0,
          "ringId": "trial",
          "date": "2020-08-06T00:00:00.000Z",
          "license": "Apache License 2.0",
          "description": "Keycloak is an Open Source Identity and Access Management solution for modern Applications and Services."
        }
      ],
      "url": "#",
      "key": "keycloak",
      "id": "keycloak",
      "title": "Keycloak",
      "quadrant": "infrastructure"
    },
    {
      "timeline": [
        {
          "moved": 0,
          "ringId": "trial",
          "date": "2020-08-06T00:00:00.000Z",
          "license": "Apache License 2.0",
          "description": "Open Policy Agent (OPA) is an open source, general-purpose policy engine that enables unified, context-aware policy enforcement across the entire stack."
        }
      ],
      "url": "#",
      "key": "open-policy-agent",
      "id": "open-policy-agent",
      "title": "Open Policy Agent",
      "quadrant": "infrastructure"
    },
    {
      "timeline": [
        {
          "moved": 0,
          "ringId": "trial",
          "date": "2020-08-06T00:00:00.000Z",
          "license": "Apache License 2.0",
          "description": "An open platform for building developer portals."
        }
      ],
      "url": "#",
      "key": "backstage",
      "id": "backstage",
      "title": "Backstage",
      "quadrant": "infrastructure"
    },
    {
      "timeline": [
        {
          "moved": 0,
          "ringId": "adopt",
          "date": "2020-08-06T00:00:00.000Z",
          "license": "Apache License 2.0",
          "description": "Helm is a tool that streamlines installing and managing Kubernetes applications. Think of it like apt/yum/homebrew for Kubernetes."
        }
      ],
      "url": "#",
      "key": "helm",
      "id": "helm",
      "title": "Helm",
      "quadrant": "tools"
    },
    {
      "timeline": [
        {
          "moved": 0,
          "ringId": "adopt",
          "date": "2020-08-06T00:00:00.000Z",
          "license": "GNU General Public License",
          "description": "Ansible is a radically simple IT automation system. It handles configuration management, application deployment, cloud provisioning, ad-hoc task execution, network automation, and multi-node orchestration. Ansible makes complex changes like zero-downtime rolling updates with load balancers easy."
        }
      ],
      "url": "#",
      "key": "ansible",
      "id": "ansible",
      "title": "Ansible",
      "quadrant": "tools"
    },
    {
      "timeline": [
        {
          "moved": 0,
          "ringId": "adopt",
          "date": "2020-08-06T00:00:00.000Z",
          "license": "Mozilla Public License 2.0",
          "description": "Terraform is a tool for building, changing, and versioning infrastructure safely and efficiently. Terraform can manage existing and popular service providers as well as custom in-house solutions."
        }
      ],
      "url": "#",
      "key": "terraform",
      "id": "terraform",
      "title": "Terraform",
      "quadrant": "tools"
    },
    {
      "timeline": [
        {
          "moved": 0,
          "ringId": "adopt",
          "date": "2020-08-06T00:00:00.000Z",
          "license": "Python Software Foundation License",
          "description": ""
        }
      ],
      "url": "#",
      "key": "python",
      "id": "python",
      "title": "Python",
      "quadrant": "languages"
    },
    {
      "timeline": [
        {
          "moved": 0,
          "ringId": "trial",
          "date": "2020-08-06T00:00:00.000Z",
          "license": "BSD 3-Clause 'New' or 'Revised' License",
          "description": ""
        }
      ],
      "url": "#",
      "key": "go",
      "id": "go",
      "title": "Go",
      "quadrant": "languages"
    },
    {
      "timeline": [
        {
          "moved": 0,
          "ringId": "adopt",
          "date": "2020-08-06T00:00:00.000Z",
          "license": "",
          "description": "Infrastructure as Code (IaC) is the managing and provisioning of infrastructure through code instead of through manual processes."
        }
      ],
      "url": "#",
      "key": "iac",
      "id": "iac",
      "title": "Infrastructure as Code",
      "quadrant": "techniques"
    }
  ]
}
